cvai_cacher/__init__.py
cvai_cacher/caching.py
cvai_cacher-0.4.12.dist-info/WHEEL
cvai_cacher-0.4.12.dist-info/METADATA
cvai_cacher-0.4.12.dist-info/RECORD
