Metadata-Version: 2.1
Name: cvai-cacher
Version: 0.4.12
Summary: ClearVision AI cacher
Author: Gautham Reddy
Author-email: gauthamv93@yaho.com
Requires-Python: >=3.6,<4.0
Classifier: Programming Language :: Python :: 3
Classifier: Programming Language :: Python :: 3.10
Classifier: Programming Language :: Python :: 3.6
Classifier: Programming Language :: Python :: 3.7
Classifier: Programming Language :: Python :: 3.8
Classifier: Programming Language :: Python :: 3.9
Requires-Dist: cvai-logger (>=0.1.4,<0.2.0)
Requires-Dist: redis (>=4.3.1,<5.0.0)
